{"3a17506750afcfb718813ece9785fea1:96797789f4669ba5e9de53cebde9126b":{"statistic":{"failed":1,"broken":0,"skipped":0,"passed":0,"unknown":0,"total":1},"items":[{"uid":"e8782d4e7864f7a2","reportUrl":"https://antnikol.github.io/gFit_playwright_tests/112//#testresult/e8782d4e7864f7a2","status":"failed","statusDetails":"Error: browserType.launch: Executable doesn't exist at /home/runner/.cache/ms-playwright/chromium_headless_shell-1161/chrome-linux/headless_shell\n╔═════════════════════════════════════════════════════════════════════════╗\n║ Looks like Playwright Test or Playwright was just installed or updated. ║\n║ Please run the following command to download new browsers:              ║\n║                                                                         ║\n║     npx playwright install                                              ║\n║                                                                         ║\n║ <3 Playwright Team                                                      ║\n╚═════════════════════════════════════════════════════════════════════════╝","time":{"start":1742416281441,"stop":1742416281447,"duration":6}}]},"9ea77b14746c44915bcc9f34c1676ac7:f0494070a4792d94c64308aac1604abb":{"statistic":{"failed":1,"broken":0,"skipped":0,"passed":0,"unknown":0,"total":1},"items":[{"uid":"2813c156e4cabbb0","reportUrl":"https://antnikol.github.io/gFit_playwright_tests/112//#testresult/2813c156e4cabbb0","status":"failed","statusDetails":"Error: browserType.launch: Executable doesn't exist at /home/runner/.cache/ms-playwright/webkit-2140/pw_run.sh\n╔═════════════════════════════════════════════════════════════════════════╗\n║ Looks like Playwright Test or Playwright was just installed or updated. ║\n║ Please run the following command to download new browsers:              ║\n║                                                                         ║\n║     npx playwright install                                              ║\n║                                                                         ║\n║ <3 Playwright Team                                                      ║\n╚═════════════════════════════════════════════════════════════════════════╝","time":{"start":1742416283486,"stop":1742416283491,"duration":5}}]},"9ea77b14746c44915bcc9f34c1676ac7:96797789f4669ba5e9de53cebde9126b":{"statistic":{"failed":1,"broken":0,"skipped":0,"passed":0,"unknown":0,"total":1},"items":[{"uid":"eccea49c2448dcd5","reportUrl":"https://antnikol.github.io/gFit_playwright_tests/112//#testresult/eccea49c2448dcd5","status":"failed","statusDetails":"Error: browserType.launch: Executable doesn't exist at /home/runner/.cache/ms-playwright/chromium_headless_shell-1161/chrome-linux/headless_shell\n╔═════════════════════════════════════════════════════════════════════════╗\n║ Looks like Playwright Test or Playwright was just installed or updated. ║\n║ Please run the following command to download new browsers:              ║\n║                                                                         ║\n║     npx playwright install                                              ║\n║                                                                         ║\n║ <3 Playwright Team                                                      ║\n╚═════════════════════════════════════════════════════════════════════════╝","time":{"start":1742416281440,"stop":1742416281445,"duration":5}}]},"3a17506750afcfb718813ece9785fea1:b444eb0fbe6390c71e68b51dd25701fc":{"statistic":{"failed":1,"broken":0,"skipped":0,"passed":0,"unknown":0,"total":1},"items":[{"uid":"87b984318e755b6d","reportUrl":"https://antnikol.github.io/gFit_playwright_tests/112//#testresult/87b984318e755b6d","status":"failed","statusDetails":"Error: browserType.launch: Executable doesn't exist at /home/runner/.cache/ms-playwright/firefox-1475/firefox/firefox\n╔═════════════════════════════════════════════════════════════════════════╗\n║ Looks like Playwright Test or Playwright was just installed or updated. ║\n║ Please run the following command to download new browsers:              ║\n║                                                                         ║\n║     npx playwright install                                              ║\n║                                                                         ║\n║ <3 Playwright Team                                                      ║\n╚═════════════════════════════════════════════════════════════════════════╝","time":{"start":1742416277299,"stop":1742416277305,"duration":6}}]},"9ea77b14746c44915bcc9f34c1676ac7:2d9eadd8e5698e677c4123f9b6b8cac6":{"statistic":{"failed":0,"broken":0,"skipped":0,"passed":1,"unknown":0,"total":1},"items":[{"uid":"a240669fda2eadee","reportUrl":"https://antnikol.github.io/gFit_playwright_tests/112//#testresult/a240669fda2eadee","status":"passed","time":{"start":1742416284163,"stop":1742416303928,"duration":19765}}]},"3a17506750afcfb718813ece9785fea1:5bd835b0d6b1d4ada3b9f0db936e82c8":{"statistic":{"failed":1,"broken":0,"skipped":0,"passed":0,"unknown":0,"total":1},"items":[{"uid":"f6cc91b780e21e68","reportUrl":"https://antnikol.github.io/gFit_playwright_tests/112//#testresult/f6cc91b780e21e68","status":"failed","statusDetails":"Error: browserType.launch: Executable doesn't exist at /home/runner/.cache/ms-playwright/chromium_headless_shell-1161/chrome-linux/headless_shell\n╔═════════════════════════════════════════════════════════════════════════╗\n║ Looks like Playwright Test or Playwright was just installed or updated. ║\n║ Please run the following command to download new browsers:              ║\n║                                                                         ║\n║     npx playwright install                                              ║\n║                                                                         ║\n║ <3 Playwright Team                                                      ║\n╚═════════════════════════════════════════════════════════════════════════╝","time":{"start":1742416275152,"stop":1742416275157,"duration":5}}]},"3a17506750afcfb718813ece9785fea1:f0494070a4792d94c64308aac1604abb":{"statistic":{"failed":1,"broken":0,"skipped":0,"passed":0,"unknown":0,"total":1},"items":[{"uid":"3440fa843b757fdd","reportUrl":"https://antnikol.github.io/gFit_playwright_tests/112//#testresult/3440fa843b757fdd","status":"failed","statusDetails":"Error: browserType.launch: Executable doesn't exist at /home/runner/.cache/ms-playwright/webkit-2140/pw_run.sh\n╔═════════════════════════════════════════════════════════════════════════╗\n║ Looks like Playwright Test or Playwright was just installed or updated. ║\n║ Please run the following command to download new browsers:              ║\n║                                                                         ║\n║     npx playwright install                                              ║\n║                                                                         ║\n║ <3 Playwright Team                                                      ║\n╚═════════════════════════════════════════════════════════════════════════╝","time":{"start":1742416283480,"stop":1742416283486,"duration":6}}]},"9ea77b14746c44915bcc9f34c1676ac7:b444eb0fbe6390c71e68b51dd25701fc":{"statistic":{"failed":1,"broken":0,"skipped":0,"passed":0,"unknown":0,"total":1},"items":[{"uid":"81502f0867e648a4","reportUrl":"https://antnikol.github.io/gFit_playwright_tests/112//#testresult/81502f0867e648a4","status":"failed","statusDetails":"Error: browserType.launch: Executable doesn't exist at /home/runner/.cache/ms-playwright/firefox-1475/firefox/firefox\n╔═════════════════════════════════════════════════════════════════════════╗\n║ Looks like Playwright Test or Playwright was just installed or updated. ║\n║ Please run the following command to download new browsers:              ║\n║                                                                         ║\n║     npx playwright install                                              ║\n║                                                                         ║\n║ <3 Playwright Team                                                      ║\n╚═════════════════════════════════════════════════════════════════════════╝","time":{"start":1742416277279,"stop":1742416277284,"duration":5}}]},"9ea77b14746c44915bcc9f34c1676ac7:5bd835b0d6b1d4ada3b9f0db936e82c8":{"statistic":{"failed":1,"broken":0,"skipped":0,"passed":0,"unknown":0,"total":1},"items":[{"uid":"a0decc68e320d653","reportUrl":"https://antnikol.github.io/gFit_playwright_tests/112//#testresult/a0decc68e320d653","status":"failed","statusDetails":"Error: browserType.launch: Executable doesn't exist at /home/runner/.cache/ms-playwright/chromium_headless_shell-1161/chrome-linux/headless_shell\n╔═════════════════════════════════════════════════════════════════════════╗\n║ Looks like Playwright Test or Playwright was just installed or updated. ║\n║ Please run the following command to download new browsers:              ║\n║                                                                         ║\n║     npx playwright install                                              ║\n║                                                                         ║\n║ <3 Playwright Team                                                      ║\n╚═════════════════════════════════════════════════════════════════════════╝","time":{"start":1742416275166,"stop":1742416275172,"duration":6}}]},"3a17506750afcfb718813ece9785fea1:4151609b82fd60da52fe302128be4a3c":{"statistic":{"failed":0,"broken":0,"skipped":0,"passed":1,"unknown":0,"total":1},"items":[{"uid":"568ba2196a5bc7f0","reportUrl":"https://antnikol.github.io/gFit_playwright_tests/112//#testresult/568ba2196a5bc7f0","status":"passed","time":{"start":1742416336909,"stop":1742416339877,"duration":2968}}]},"9ea77b14746c44915bcc9f34c1676ac7:4151609b82fd60da52fe302128be4a3c":{"statistic":{"failed":0,"broken":0,"skipped":0,"passed":1,"unknown":0,"total":1},"items":[{"uid":"6c44dfd27c43ab4c","reportUrl":"https://antnikol.github.io/gFit_playwright_tests/112//#testresult/6c44dfd27c43ab4c","status":"passed","time":{"start":1742416336689,"stop":1742416339453,"duration":2764}}]},"3a17506750afcfb718813ece9785fea1:2d9eadd8e5698e677c4123f9b6b8cac6":{"statistic":{"failed":0,"broken":0,"skipped":0,"passed":1,"unknown":0,"total":1},"items":[{"uid":"67ac72a48b58e415","reportUrl":"https://antnikol.github.io/gFit_playwright_tests/112//#testresult/67ac72a48b58e415","status":"passed","time":{"start":1742416284163,"stop":1742416304413,"duration":20250}}]},"9ea77b14746c44915bcc9f34c1676ac7:84e28e814b821ed013329cc8dbc467e0":{"statistic":{"failed":1,"broken":0,"skipped":0,"passed":0,"unknown":0,"total":1},"items":[{"uid":"574d0e675f316c06","reportUrl":"https://antnikol.github.io/gFit_playwright_tests/112//#testresult/574d0e675f316c06","status":"failed","statusDetails":"Error: browserType.launch: Executable doesn't exist at /home/runner/.cache/ms-playwright/webkit-2140/pw_run.sh\n╔═════════════════════════════════════════════════════════════════════════╗\n║ Looks like Playwright Test or Playwright was just installed or updated. ║\n║ Please run the following command to download new browsers:              ║\n║                                                                         ║\n║     npx playwright install                                              ║\n║                                                                         ║\n║ <3 Playwright Team                                                      ║\n╚═════════════════════════════════════════════════════════════════════════╝","time":{"start":1742416279380,"stop":1742416279387,"duration":7}}]},"3a17506750afcfb718813ece9785fea1:84e28e814b821ed013329cc8dbc467e0":{"statistic":{"failed":1,"broken":0,"skipped":0,"passed":0,"unknown":0,"total":1},"items":[{"uid":"f91cbe66381e3c03","reportUrl":"https://antnikol.github.io/gFit_playwright_tests/112//#testresult/f91cbe66381e3c03","status":"failed","statusDetails":"Error: browserType.launch: Executable doesn't exist at /home/runner/.cache/ms-playwright/webkit-2140/pw_run.sh\n╔═════════════════════════════════════════════════════════════════════════╗\n║ Looks like Playwright Test or Playwright was just installed or updated. ║\n║ Please run the following command to download new browsers:              ║\n║                                                                         ║\n║     npx playwright install                                              ║\n║                                                                         ║\n║ <3 Playwright Team                                                      ║\n╚═════════════════════════════════════════════════════════════════════════╝","time":{"start":1742416279388,"stop":1742416279394,"duration":6}}]}}